pyplotterlib/__init__.py
pyplotterlib/core/__init__.py
pyplotterlib/core/json_transform.py
pyplotterlib/core/plot_command.py
pyplotterlib/core/plot_options.py
pyplotterlib/core/plotters.py
pyplotterlib/core/serialization/__init__.py
pyplotterlib/core/serialization/json_io.py
pyplotterlib/core/serialization/register.py
pyplotterlib/core/serialization/registration_funct.py
pyplotterlib/core/serialization/unit_tests/__init__.py
pyplotterlib/core/serialization/unit_tests/utest_create_from_json.py
pyplotterlib/core/unit_tests/__init__.py
pyplotterlib/core/unit_tests/utest_plot_options.py
pyplotterlib/core/unit_tests/utest_plotters.py
pyplotterlib/reg_testing/__init__.py
pyplotterlib/reg_testing/shared.py
pyplotterlib/reg_testing/read_serialization_test/__init__.py
pyplotterlib/reg_testing/read_serialization_test/helpers.py
pyplotterlib/reg_testing/viz_diff/__init__.py
pyplotterlib/reg_testing/viz_diff/helpers.py
pyplotterlib/standard/__init__.py
pyplotterlib/standard/annotations.py
pyplotterlib/standard/plot_commands.py
pyplotterlib/standard/plot_options.py
pyplotterlib/standard/plotters.py
pyplotterlib/standard/serialization.py
pyplotterlib/standard/private/__init__.py
pyplotterlib/standard/private/bar_plotter.py
pyplotterlib/standard/private/box_plotter.py
pyplotterlib/standard/private/disc_heat_plotter.py
pyplotterlib/standard/private/histogram_plotter.py
pyplotterlib/standard/private/image_plotter.py
pyplotterlib/standard/private/line_plotter.py
pyplotterlib/standard/private/rect_multi_plotter.py
pyplotterlib/standard/private/shared.py
pyplotterlib/standard/private/shared_axis_plotter.py
pyplotterlib/standard/private/split_axis_plotter.py
pyplotterlib/standard/private/split_axis_plotter_creator.py
pyplotterlib/standard/private/unit_tests/__init__.py
pyplotterlib/standard/private/unit_tests/utests_histogram_plotter.py
pyplotterlib/standard/unit_tests/__init__.py
pyplotterlib/standard/unit_tests/utests_plot_commands.py
pyplotterlib-1.8.0.dist-info/LICENSE
pyplotterlib-1.8.0.dist-info/METADATA
pyplotterlib-1.8.0.dist-info/WHEEL
pyplotterlib-1.8.0.dist-info/top_level.txt
pyplotterlib-1.8.0.dist-info/RECORD
