Metadata-Version: 2.1
Name: pyplotterlib
Version: 1.8.0
Summary: A package used to create plots in python
Author-email: Richard Fogarty <richard.m.fogarty@gmail.com>
License: MIT License
Project-URL: Documentation, https://pyplotterlib.readthedocs.io/en/latest/index.html
Project-URL: Github, https://github.com/RFogarty1/pyplotterlib
Classifier: Framework :: Matplotlib
Classifier: License :: OSI Approved :: MIT License
Classifier: Programming Language :: Python
Classifier: Programming Language :: Python :: 3
Classifier: Topic :: Scientific/Engineering :: Visualization
License-File: LICENSE
Requires-Dist: numpy
Requires-Dist: matplotlib
Provides-Extra: dev
Requires-Dist: numpy ==1.22.2 ; extra == 'dev'
Requires-Dist: matplotlib ==3.5.1 ; extra == 'dev'
Requires-Dist: matplotlib-inline ==0.1.3 ; extra == 'dev'
Requires-Dist: ipython ==8.4.0 ; extra == 'dev'
Requires-Dist: ipyplot ==1.1.1 ; extra == 'dev'
Requires-Dist: pydataset ; extra == 'dev'
Requires-Dist: notebook ==6.4.12 ; extra == 'dev'
Provides-Extra: pinned
Requires-Dist: numpy ==1.22.2 ; extra == 'pinned'
Requires-Dist: matplotlib ==3.5.1 ; extra == 'pinned'
